wigeon/__init__.py
wigeon/__main__.py
wigeon/commands.py
wigeon/db.py
wigeon/levels.py
wigeon/main.py
wigeon/manifests.py
wigeon/packages.py
wigeon-0.1.3.dist-info/LICENSE
wigeon-0.1.3.dist-info/METADATA
wigeon-0.1.3.dist-info/WHEEL
wigeon-0.1.3.dist-info/entry_points.txt
wigeon-0.1.3.dist-info/top_level.txt
wigeon-0.1.3.dist-info/RECORD
