Metadata-Version: 2.1
Name: wigeon
Version: 0.1.3
Summary: DB Migrations for the continuous developer.
Home-page: https://github.com/JLRitch/wigeon
Author: Jere Ritchie
Author-email: jereritchie@gmail.com
License: BSD
Project-URL: Source, https://github.com/
Platform: UNKNOWN
Classifier: License :: OSI Approved :: BSD License
Classifier: Operating System :: OS Independent
Classifier: Programming Language :: Python :: 3
Classifier: Programming Language :: Python :: 3.7
Classifier: Programming Language :: Python :: 3.8
Classifier: Programming Language :: Python :: 3.9
Classifier: Programming Language :: Python :: 3.10
Classifier: Programming Language :: Python :: Implementation :: CPython
Requires-Python: >=3.7
License-File: LICENSE
Requires-Dist: click (>=8.0.3)
Requires-Dist: pymssql (>=2.2.4)
